polymatheia/__init__.py
polymatheia/data/__init__.py
polymatheia/data/reader.py
polymatheia/data/writer.py
polymatheia/filter.py
polymatheia/transform.py
polymatheia/util.py
polymatheia-1.1.0.dist-info/LICENSE.md
polymatheia-1.1.0.dist-info/METADATA
polymatheia-1.1.0.dist-info/WHEEL
polymatheia-1.1.0.dist-info/RECORD
