Metadata-Version: 2.3
Name: polymatheia
Version: 1.1.0
Summary: A python library to support digital archive metadata use
License: MIT
Author: Mark Hall
Author-email: mark.hall@work.room3b.eu
Requires-Python: >=3.11,<3.13
Classifier: Development Status :: 4 - Beta
Classifier: Intended Audience :: Education
Classifier: Intended Audience :: Science/Research
Classifier: License :: OSI Approved :: MIT License
Classifier: Programming Language :: Python :: 3
Classifier: Programming Language :: Python :: 3.11
Classifier: Programming Language :: Python :: 3.12
Classifier: Programming Language :: Python :: 3.7
Classifier: Programming Language :: Python :: 3.8
Classifier: Topic :: Education
Classifier: Topic :: Scientific/Engineering
Classifier: Topic :: Software Development :: Libraries
Requires-Dist: Sickle (>=0.7.0,<0.8.0)
Requires-Dist: deprecation (>=2.1.0,<3.0.0)
Requires-Dist: lxml (>=4.5.2,<5.0.0)
Requires-Dist: munch (>=4.0.0,<5.0.0)
Requires-Dist: pandas (>=2.2.3,<3.0.0)
Requires-Dist: requests (>=2.32.3,<3.0.0)
Requires-Dist: srupy (>=0.1.1,<0.2.0)
Project-URL: Homepage, https://polymatheia.readthedocs.io
Project-URL: Repository, https://github.com/scmmmh/polymatheia
